ds_search_service/__init__.py
ds_search_service/api/__init__.py
ds_search_service/api/decentralized_search_api.py
ds_search_service/api/default_api.py
ds_search_service/api/items_api.py
ds_search_service/api/local_search_api.py
ds_search_service/api_client.py
ds_search_service/api_response.py
ds_search_service/configuration.py
ds_search_service/exceptions.py
ds_search_service/models/__init__.py
ds_search_service/models/catalog_filters.py
ds_search_service/models/example_response.py
ds_search_service/models/health_check.py
ds_search_service/models/http_validation_error.py
ds_search_service/models/item.py
ds_search_service/models/validation_error.py
ds_search_service/models/validation_error_loc_inner.py
ds_search_service/py.typed
ds_search_service/rest.py
ds_search_service-0.2.2.dist-info/LICENSE
ds_search_service-0.2.2.dist-info/METADATA
ds_search_service-0.2.2.dist-info/WHEEL
ds_search_service-0.2.2.dist-info/RECORD
